VetstoriaNER/EntityRecognizer.py
VetstoriaNER/__init__.py
VetstoriaNER-0.8.dist-info/LICENSE.txt
VetstoriaNER-0.8.dist-info/METADATA
VetstoriaNER-0.8.dist-info/WHEEL
VetstoriaNER-0.8.dist-info/top_level.txt
VetstoriaNER-0.8.dist-info/RECORD
