Metadata-Version: 2.1
Name: VetstoriaNER
Version: 0.8
Summary: Species detection package for Vetstoria
Home-page: UNKNOWN
Author: Vetstoria
Author-email: hasvin@vetstoria.com, riza@vetstoria.com
License: UNKNOWN
Platform: UNKNOWN
Classifier: Intended Audience :: Developers
Classifier: License :: OSI Approved :: MIT License
Classifier: Natural Language :: English
Classifier: Operating System :: OS Independent
Classifier: Programming Language :: Python
Requires-Python: >=3.6.9
License-File: LICENSE.txt
Requires-Dist: spacy
